deck/__init__.py
deck/api.py
deck/models.py
nextcloud_deck-0.2.1.dist-info/METADATA
nextcloud_deck-0.2.1.dist-info/WHEEL
nextcloud_deck-0.2.1.dist-info/RECORD
